indie/__init__.py
indie/__main__.py
indie/script/create_usb_installer.sh
indie/script/first_boot.sh
indie/script/first_boot_wrapper.sh
indie/script/install_openwrt_lxc.sh
indie-0.1.36.dist-info/licenses/LICENSE
indie-0.1.36.dist-info/METADATA
indie-0.1.36.dist-info/WHEEL
indie-0.1.36.dist-info/entry_points.txt
indie-0.1.36.dist-info/top_level.txt
indie-0.1.36.dist-info/RECORD
