Metadata-Version: 2.4
Name: indie
Version: 0.1.36
Summary: An initiative to allow small indie gamedev studios to deploy complex server infrastructure with ease
Author-email: Fredrik Zetterman <fredrik.zetterman@rodengames.com>
License: MIT License
Project-URL: Homepage, https://github.com/fredrikkz/indie-infrastructure-initiative
Keywords: proxmox,indie
Classifier: License :: OSI Approved :: MIT License
Classifier: Programming Language :: Python
Classifier: Programming Language :: Python :: 3
Requires-Python: >=3.11
License-File: LICENSE
Requires-Dist: tomlkit>=0.13.3
Requires-Dist: aiohttp>=3.12.15
Requires-Dist: geocoder>=1.1.4
Requires-Dist: pycountry>=24.6.1
Requires-Dist: validators>=0.35.0
Requires-Dist: tzlocal>=5.3.1
Requires-Dist: passlib>=1.7.4
Requires-Dist: cryptography>=45.0.6
Provides-Extra: dev
Requires-Dist: bumpver; extra == "dev"
Dynamic: license-file
